versionpy/__init__.py
versionpy/_version.py
versionpy-0.4.11.data/scripts/bump
versionpy-0.4.11.data/scripts/increment_version
versionpy-0.4.11.data/scripts/version
versionpy-0.4.11.dist-info/LICENSE
versionpy-0.4.11.dist-info/METADATA
versionpy-0.4.11.dist-info/WHEEL
versionpy-0.4.11.dist-info/top_level.txt
versionpy-0.4.11.dist-info/RECORD
