Metadata-Version: 2.1
Name: versionpy
Version: 0.4.11
Summary: Small utility to track and bump the version of your python tool
Home-page: https://github.com/vladsaveliev/versionpy
Author: Vlad Savelyev
Author-email: vladislav.sav@gmail.com
License: GPLv3
Keywords: bioinformatics
Platform: UNKNOWN
Classifier: Environment :: Console
Classifier: Intended Audience :: Science/Research
Classifier: License :: OSI Approved :: GNU General Public License v3 (GPLv3)
Classifier: Natural Language :: English
Classifier: Operating System :: MacOS :: MacOS X
Classifier: Operating System :: POSIX
Classifier: Operating System :: Unix
Classifier: Programming Language :: Python
Classifier: Topic :: Scientific/Engineering
Requires-Python: >=3.6
Requires-Dist: click
